{
    "name": "Basestation Release",
    "build": {
        "dockerfile": "Dockerfile"
    },
    "customizations": {
        "vscode": {
            "extensions": [
                "ms-python.python",
                "ms-python.black-formatter",
                "ms-vscode.cpptools",
                "ms-vscode.vscode-typescript-next",
                "DavidAnson.vscode-markdownlint",
                "yzhang.markdown-all-in-one",
                "streetsidesoftware.code-spell-checker",
                "ms-azuretools.vscode-docker",
                "ms-iot.vscode-ros",
                "dbaeumer.vscode-eslint",
                "svelte.svelte-vscode",
                "eamodio.gitlens",
                "ardenivanov.svelte-intellisense"
            ]
        }
    },
    "updateRemoteUserUID": true,
    "runArgs": [
        "--network=host"
    ],
    "postStartCommand": "sudo caddy start"
}